.DS_Store
spatial_summarize_within/__init__.py
spatial_summarize_within/max_within.py
spatial_summarize_within/mean_within.py
spatial_summarize_within/min_within.py
spatial_summarize_within/sum_within.py
spatial_summarize_within-1.0.6.dist-info/LICENSE
spatial_summarize_within-1.0.6.dist-info/METADATA
spatial_summarize_within-1.0.6.dist-info/WHEEL
spatial_summarize_within-1.0.6.dist-info/top_level.txt
spatial_summarize_within-1.0.6.dist-info/RECORD
